entity_classification/__init__.py
entity_classification/bp/__init__.py
entity_classification/bp/entity_orchestrator.py
entity_classification/dmo/__init__.py
entity_classification/svc/__init__.py
entity_classification/svc/analyze_entity_names.py
entity_classification/svc/find_entity_triggers.py
entity_classification/svc/form_entity_inference.py
entity_classification-0.1.3.dist-info/WHEEL
entity_classification-0.1.3.dist-info/METADATA
entity_classification-0.1.3.dist-info/RECORD
