Metadata-Version: 2.1
Name: entity-classification
Version: 0.1.3
Summary: Perform Intent Classification using a list of Entities
Home-page: https://github.com/craigtrim/entity-classification
License: MIT
Keywords: nlp,nlu,ai,classification,intents
Author: Craig Trim
Author-email: craigtrim@gmail.com
Maintainer: Craig Trim
Maintainer-email: craigtrim@gmail.com
Requires-Python: >=3.8.5,<4.0.0
Classifier: Development Status :: 4 - Beta
Classifier: License :: OSI Approved :: MIT License
Classifier: Programming Language :: Python :: 3
Classifier: Programming Language :: Python :: 3.10
Classifier: Programming Language :: Python :: 3.9
Classifier: Topic :: Scientific/Engineering :: Artificial Intelligence
Classifier: Topic :: Software Development :: Libraries :: Python Modules
Requires-Dist: baseblock
Project-URL: Repository, https://github.com/craigtrim/entity-classification
